moorellm-0.1.9.dist-info/METADATA
moorellm-0.1.9.dist-info/WHEEL
moorellm-0.1.9.dist-info/entry_points.txt
moorellm/__init__.py
moorellm/main.py
moorellm/misc.py
moorellm/models.py
moorellm/utils.py
moorellm-0.1.9.dist-info/RECORD
