Metadata-Version: 2.1
Name: MooreLLM
Version: 0.1.9
Summary: Moore's State Machine based Agent LLMs
Author-Email: Harishankar Kumar <hari01584@gmail.com>
License: MIT
Project-URL: Homepage, https://github.com/searchX/moorellm
Requires-Python: >=3.9
Requires-Dist: pydantic>=2.8.2
Requires-Dist: openai>=1.40.6
Requires-Dist: Jinja2>=3.1.4
